[
  {
    "address": "\n\nTuscaloosa, Alabama 35406\n\n\n(844) 291-6342\n\n\n",
    "url": "https://www.psychologytoday.com/us/therapists/ariela-h-aaron-tuscaloosa-al/427498"
  },
  {
    "address": "\n\n                                        Grace Point Behavioral\n\n                    1331 Old Oak Place\n                \nMontgomery, Alabama 36117\n\nCall Dr. Caroline Abolade\n\n(334) 384-6354\n\n\n",
    "url": "https://www.psychologytoday.com/us/psychiatrists/grace-point-behavioral-montgomery-al/302098"
  },
  {
    "address": "\n\n                                        Comprehensive MedPsych Systems\n\n                    1110 Montlimar Place\n                \n            \n                            Suite 500\nMobile, Alabama 36609\n\n\n(251) 220-3095\n\n\n",
    "url": "https://www.psychologytoday.com/us/psychiatrists/bayani-alberto-y-abordo-mobile-al/347403"
  },
  {
    "address": "\n\n                                        Acra Behavioral Health & Consulting, LLC\n\n                    127 E College Street\n                \nEnterprise, Alabama 36330\n\n\n(334) 417-0385\n\n\n",
    "url": "https://www.psychologytoday.com/us/therapists/c-francoise-acra-enterprise-al/378355"
  },
  {
    "address": "\n\n                                        Center For Marriage & Family Therapy\n\n                    116 Lily Flagg Rd SW Ste D\n                \nHuntsville, Alabama 35802\n\n\n(256) 305-4102\n\n\n",
    "url": "https://www.psychologytoday.com/us/therapists/brandon-lee-adair-huntsville-al/328640"
  },
  {
    "address": "\n\n                                        Amelia Adams Counseling Services, LLC\n\n                    1643 Slaughter Road\n                \nMadison, Alabama 35758\n\n\n(256) 639-5558\n\n\n",
    "url": "https://www.psychologytoday.com/us/therapists/amelia-m-adams-madison-al/232846"
  },
  {
    "address": "\n\n                                        Carol G. Adams, LCSW\nTuscaloosa, Alabama 35405\n\nCall Carol Adams\n\n(205) 289-3139\n\n\n",
    "url": "https://www.psychologytoday.com/us/therapists/carol-g-adams-lcsw-tuscaloosa-al/57150"
  },
  {
    "address": "\n\n                                        Gina Adams Counseling Services\nDothan, Alabama 36305\n\n\n(334) 539-5625\n\n\n",
    "url": "https://www.psychologytoday.com/us/therapists/gina-adams-dothan-al/197962"
  },
  {
    "address": "\n\n                                        GulfWinds Montgomery\n\n                    3198 Parliament Circle\n                \n            \n                            Suite 303\nMontgomery, Alabama 36116\n\n\n(334) 226-5692\n\n\n",
    "url": "https://www.psychologytoday.com/us/therapists/donna-adams-weiss-montgomery-al/124581"
  },
  {
    "address": "\n\n                                        Adaway and Associates\n\n                    1602 Cogswell Avenue\n                \nPell City, Alabama 35125\n\n\n(205) 535-1681\n\n\n",
    "url": "https://www.psychologytoday.com/us/therapists/vicki-adaway-pell-city-al/93929"
  },
  {
    "address": "\n\n                                        Sofia Aeschlimann, MD LLC\n\n                    1015 Airport Road\n                \n            \n                            Suite 204\nHuntsville, Alabama 35802\n\n\n(256) 414-4483\n\n\n",
    "url": "https://www.psychologytoday.com/us/psychiatrists/sofia-lizbeth-aeschlimann-huntsville-al/229001"
  },
  {
    "address": "\n\n                                        Afangideh Therapy\n\n                    39 Carol Villa Drive (suite 39A)\n                \n            \n                            Suite 220\nMontgomery, Alabama 36109\n\nCall Uduak Afangideh\n\n(334) 564-9637\n\n\n",
    "url": "https://www.psychologytoday.com/us/therapists/afangideh-therapy-montgomery-al/368720"
  },
  {
    "address": "\n\n                                        Wellness Office PC\n\n                    333 Whitesport Dr\n                \n            \n                            Suite 201\nHuntsville, Alabama 35801\n\n\n(256) 388-2040\n\n\n",
    "url": "https://www.psychologytoday.com/us/psychiatrists/quratulain-agha-huntsville-al/371176"
  },
  {
    "address": "\n\n                                        Ahlers Counseling LLC\n\n                    4 Office Park Circle\n                \n            \n                            204\nBirmingham, Alabama 35223\n\n\n(205) 282-9041\n\n\n",
    "url": "https://www.psychologytoday.com/us/therapists/fred-ahlers-birmingham-al/72468"
  },
  {
    "address": "\n\n                                        Albright Counseling\n\n                    402 Office Park Drive\n                \n            \n                            Suite 210\nMountain Brook, Alabama 35223\n\n\n(205) 918-8173\n\n\n",
    "url": "https://www.psychologytoday.com/us/therapists/kate-tinney-albright-mountain-brook-al/137459"
  },
  {
    "address": "\n\n                                        Healing Grace Counseling\n\n                    936 Jeff Rd\n                \nHuntsville, Alabama 35806\n\nCall Mrs. Natalie Alexander\n\n(256) 667-1252\n\n\n",
    "url": "https://www.psychologytoday.com/us/therapists/healing-grace-counseling-huntsville-al/325464"
  },
  {
    "address": "\n\n                                        Gateway to Wellness\n\n                    400 Vestavia Parkway\n                \n            \n                            Suite 135\nVestavia Hills, Alabama 35216\n\nCall Mrs. Tyana Alexander\n\n(205) 319-7016\n\n\n",
    "url": "https://www.psychologytoday.com/us/therapists/gateway-to-wellness-vestavia-hills-al/180079"
  },
  {
    "address": "\n\n                                        Grayson & Associates \n\n                    3000 Riverchase Galeria\n                \n            \n                            Suite 500\nHoover, Alabama 35244\n\n\n(833) 267-0162\n\n\n",
    "url": "https://www.psychologytoday.com/us/psychiatrists/latisha-ali-hoover-al/456917"
  },
  {
    "address": "\n\n                                        Longwood Psychological Center\n\n                    111 Longwood Dr\n                \nHuntsville, Alabama 35801\n\n\n(256) 415-4302\n\n\n",
    "url": "https://www.psychologytoday.com/us/therapists/cathy-altonji-huntsville-al/352134"
  },
  {
    "address": "\n\n                                        Lacey Amos Counseling\n\n                    1628 29th Court South\n                \n            \n                            Suite 201\nHomewood, Alabama 35209\n\n\n(205) 289-3497\n\n\n",
    "url": "https://www.psychologytoday.com/us/therapists/lacey-amos-homewood-al/175617"
  },
  {
    "address": "\n\n\n                    Riviera Executive Complex 2690 S Mckenzie Street\n                \n            \n                            Suite 106\nFoley, Alabama 36535\n\n\n(251) 243-4552\n\n\n",
    "url": "https://www.psychologytoday.com/us/therapists/sarah-s-anderson-foley-al/205552"
  },
  {
    "address": "\n\n                                        Bay Area Clinical Associates\n\n                    3925 Springhill Ave\n                \n            \n                            Suite B\nMobile, Alabama 36608\n\n\n(251) 732-2562\n\n\n",
    "url": "https://www.psychologytoday.com/us/therapists/catalina-mandoki-arata-mobile-al/168766"
  },
  {
    "address": "\n\n                                        Counseling Services\n\n                    216 Madison Street\n                \nAlexander City, Alabama 35010\n\n\n(256) 841-7387\n\n\n",
    "url": "https://www.psychologytoday.com/us/therapists/virginia-ginny-bradshaw-archer-alexander-city-al/286213"
  },
  {
    "address": "\n\n                                        Sojourn Counseling\n\n                    300 Vestavia Parkway\n                \n            \n                            Suite 3900\nVestavia Hills, Alabama 35216\n\n\n(205) 479-3619\n\n\n",
    "url": "https://www.psychologytoday.com/us/therapists/beau-armistead-vestavia-hills-al/118881"
  },
  {
    "address": "\n\n                                        Alexander Counseling Services\n\n                    300 Office Park Drive\n                \n            \n                            Suite 220\nBirmingham, Alabama 35223\n\n\n(205) 590-5276\n\n\n",
    "url": "https://www.psychologytoday.com/us/therapists/lucinda-armstrong-birmingham-al/342367"
  },
  {
    "address": "\n\n                                        Counseling Consultation Services\n\n                    4800 Whitesport Circle\n                \n            \n                            Suite 2\nHuntsville, Alabama 35801\n\n\n(256) 808-2454\n\n\n",
    "url": "https://www.psychologytoday.com/us/therapists/grace-a-arnold-huntsville-al/384457"
  },
  {
    "address": "\n\n                                        Ashley Counseling Services, LLC\n\n                    401 E Tombigbee Street\n                \nFlorence, Alabama 35630\n\n\n(855) 681-8965\n\n\n",
    "url": "https://www.psychologytoday.com/us/therapists/misti-ashley-florence-al/244758"
  },
  {
    "address": "\n\n                                        J L Austin Counseling & Consulting\n\n                    530 Beacon Pkwy West\n                \n            \n                            Suite 401\nHomewood, Alabama 35209\n\nCall Mr. Jacques Austin\n\n(205) 677-0563\n\n\n",
    "url": "https://www.psychologytoday.com/us/therapists/j-l-austin-counseling-consulting-homewood-al/365907"
  },
  {
    "address": "\n\n                                        KB Avsar\n\n                    1025 23rd Street South\n                \n            \n                            Suite 385\nBirmingham, Alabama 35205\n\n\n(205) 302-7464\n\n\n",
    "url": "https://www.psychologytoday.com/us/therapists/kathy-burton-avsar-birmingham-al/285599"
  },
  {
    "address": "\n\n                                        Soul-Affirming Counseling\nAuburn, Alabama 36830\n\n\n(334) 539-8051\n\n\n",
    "url": "https://www.psychologytoday.com/us/therapists/kerry-baharanyi-auburn-al/328706"
  },
  {
    "address": "\n\n                                        Freedom Professional Counseling\n\n                    3 Office Park Circle \n                \n            \n                            Suite 105\nMountain Brook, Alabama 35223\n\n\n(205) 378-6221\n\n\n",
    "url": "https://www.psychologytoday.com/us/therapists/ashley-bailey-mountain-brook-al/395213"
  },
  {
    "address": "\n\n\n                    7051 Fain Park Drive\n                \n            \n                            Ste 125\nMontgomery, Alabama 36117\n\n\n(334) 954-1207\n\n\n",
    "url": "https://www.psychologytoday.com/us/therapists/candace-bailey-montgomery-al/451664"
  },
  {
    "address": "\n\n                                        The Centre\n\n                    3811 Old Shell Road\n                \n            \n                            Building 3\nMobile, Alabama 36608\n\n\n(251) 929-8945\n\n\n",
    "url": "https://www.psychologytoday.com/us/therapists/amanda-balena-mobile-al/325468"
  },
  {
    "address": "\n\n                                        Restore Counseling Services\n\n                    2053 Old Montgomery Hwy\n                \nBirmingham, Alabama 35244\n\nCall Mrs. Maggie Banger\n\n(205) 512-3071\n\n\n",
    "url": "https://www.psychologytoday.com/us/therapists/restore-counseling-services-birmingham-al/358187"
  },
  {
    "address": "\n\nSulligent, Alabama 35586\n\n\n(833) 706-5459\n\n\n",
    "url": "https://www.psychologytoday.com/us/therapists/joe-mack-bankhead-sulligent-al/414099"
  },
  {
    "address": "\n\n\n                    PO Box 1427\n                \nCalera, Alabama 35040\n\n\n(205) 668-5179\n\n\n",
    "url": "https://www.psychologytoday.com/us/therapists/lashanda-banks-calera-al/250080"
  },
  {
    "address": "\n\n                                        Red Bird Counseling LLC\n\n                    207 Eustis Avenue\n                \n            \n                            Suite E\nHuntsville, Alabama 35801\n\n\n(256) 804-0915\n\n\n",
    "url": "https://www.psychologytoday.com/us/therapists/susan-banks-norton-huntsville-al/361139"
  },
  {
    "address": "\n\n                                        The Counseling Corner\n\n                    300 State Street\n                \nMobile, Alabama 36603\n\n\n(251) 281-0514\n\n\n",
    "url": "https://www.psychologytoday.com/us/therapists/anna-barksdale-mobile-al/103663"
  },
  {
    "address": "\n\n\n                    Building 3 \n                \n            \n                            Suite 110\nBirmingham, Alabama 35223\n\nCall Mr. Millard Barnes\n\n(205) 910-4573\n\n\n",
    "url": "https://www.psychologytoday.com/us/therapists/grace-counseling-service-birmingham-al/432188"
  },
  {
    "address": "\n\n                                        Behavioral Sciences of Alabama, Inc.\n\n                    810 Shoney Drive\n                \n            \n                            Suite 120\nHuntsville, Alabama 35801\n\n\n(256) 248-7750\n\n\n",
    "url": "https://www.psychologytoday.com/us/therapists/david-l-barnhart-huntsville-al/34497"
  },
  {
    "address": "\n\n                                        Iron City Counseling\n\n                    2125 Data Office Drive\n                \n            \n                            Suite 101\nHoover, Alabama 35244\n\n\n(205) 236-1561\n\n\n",
    "url": "https://www.psychologytoday.com/us/therapists/erica-nicole-barron-hoover-al/302452"
  },
  {
    "address": "\n\nJacksonville, Alabama 36265\n\n\n(256) 600-2193\n\n\n",
    "url": "https://www.psychologytoday.com/us/therapists/chandra-bartholomew-jones-jacksonville-al/416843"
  },
  {
    "address": "\n\n                                        Bass Assertive Solutions & Support, LLC\n\n                    85 Bagby Drive\n                \n            \n                            Suite 336\nHomewood, Alabama 35209\n\nCall Dalila Bass\n\n(205) 703-2877\n\n\n",
    "url": "https://www.psychologytoday.com/us/therapists/bass-assertive-solutions-support-llc-homewood-al/407468"
  },
  {
    "address": "\n\n\n                    3737 Government Blvd\n                \n            \n                            Suite 203\nMobile, Alabama 36693\n\n\n(251) 220-3028\n\n\n",
    "url": "https://www.psychologytoday.com/us/therapists/nathan-baughn-mobile-al/442972"
  },
  {
    "address": "\n\n                                        Covenant Counseling & Consulting\n\n                    1230 Slaughter Road\n                \n            \n                            Suite F\nMadison, Alabama 35758\n\n\n(256) 840-7167\n\n\n",
    "url": "https://www.psychologytoday.com/us/therapists/mark-allen-beaird-madison-al/258359"
  },
  {
    "address": "\n\n\n                    250 Sun Temple Drive\n                \nMadison, Alabama 35758\n\n\n(938) 777-0250\n\n\n",
    "url": "https://www.psychologytoday.com/us/therapists/pearl-behavioral-health-services-madison-al/453744"
  },
  {
    "address": "\n\n                                        LifeBoat Coaching\n\n                    445 Dexter Ave\n                \n            \n                            Suite 4050\nMontgomery, Alabama 36104\n\n\n(334) 247-6345\n\n\n",
    "url": "https://www.psychologytoday.com/us/therapists/sam-belkofer-montgomery-al/200405"
  },
  {
    "address": "\n\n                                        Restore Counseling Services\n\n                    8089 Highway 72 West\n                \n            \n                            Suite D\nMadison, Alabama 35758\n\n\n(256) 305-1184\n\n\n",
    "url": "https://www.psychologytoday.com/us/therapists/willie-s-bell-madison-al/294204"
  },
  {
    "address": "\n\n                                        Comprehensive MedPsych Systems\n\n                    1110 Montlimar Place\n                \n            \n                            Suite 500\nMobile, Alabama 36609\n\n\n(251) 241-8056\n\n\n",
    "url": "https://www.psychologytoday.com/us/psychiatrists/jonathan-benaknin-mobile-al/347662"
  },
  {
    "address": "\n\n                                        Barbara Bernstein, MA, LLC\n\n                    2112 11th Ave South\n                \n            \n                            Suite 325\nBirmingham, Alabama 35205\n\n\n(205) 322-1818\n\n\n",
    "url": "https://www.psychologytoday.com/us/therapists/barbara-bernstein-birmingham-al/72815"
  },
  {
    "address": "\n\n\n                    187 Belmont Drive\n                \nDothan, Alabama 36305\n\n\n(334) 232-9949\n\n\n",
    "url": "https://www.psychologytoday.com/us/therapists/kimberly-a-berry-dothan-al/59912"
  },
  {
    "address": "\n\n                                        Berryhill Wellness & Counseling, LLC\n\n                    4513 Valleydale Road\n                \n            \n                            Suite 2\nBirmingham, Alabama 35242\n\n\n(205) 623-5917\n\n\n",
    "url": "https://www.psychologytoday.com/us/therapists/ellery-c-berryhill-birmingham-al/166174"
  },
  {
    "address": "\n\n                                        Auburn Professional Counseling\nAuburn, Alabama 36830\n\n\n(334) 375-9275\n\n\n",
    "url": "https://www.psychologytoday.com/us/therapists/cyrilla-adgate-beveridge-auburn-al/242263"
  },
  {
    "address": "\n\n                                        Bevill and Associates\n\n                    2524 Valleydale Road\n                \n            \n                            Suite 100\nBirmingham, Alabama 35244\n\n\n(205) 224-0063 x1\n\n\n",
    "url": "https://www.psychologytoday.com/us/therapists/al-bevill-birmingham-al/145263"
  },
  {
    "address": "\n\n                                        Ella Bevis Counseling, LLC\n\n                    118 East Mobile Street\n                \n            \n                            Suite 307\nFlorence, Alabama 35630\n\nCall Ella Bevis\n\n(256) 760-1211\n\n\n",
    "url": "https://www.psychologytoday.com/us/therapists/ella-bevis-counseling-llc-florence-al/245179"
  },
  {
    "address": "\n\n\n                    7085 Sydney Curve\n                \nMontgomery, Alabama 36117\n\n\n(334) 487-1003\n\n\n",
    "url": "https://www.psychologytoday.com/us/therapists/brady-beziat-montgomery-al/424152"
  },
  {
    "address": "\n\n\n                    6348 Piccadilly Square Drive\n                \n            \n                            Suite 215\nMobile, Alabama 36609\n\n\n(251) 262-2796\n\n\n",
    "url": "https://www.psychologytoday.com/us/therapists/shivani-bhakta-mobile-al/441179"
  },
  {
    "address": "\n\n                                        Longwood Psychological Center\n\n                    111 Longwood Drive\n                \nHuntsville, Alabama 35801\n\n\n(256) 414-8125\n\n\n",
    "url": "https://www.psychologytoday.com/us/therapists/margaret-bibb-huntsville-al/306937"
  },
  {
    "address": "\n\n                                        Magnolia Creek Treatment Ctr for Eating Disorders\n\n                    162 Magnolia Creek Drive\n                \nColumbiana, Alabama 35051\n\nCall Meranda Bice\n\n(855) 687-1060\n\n\n",
    "url": "https://www.psychologytoday.com/us/treatment-rehab/magnolia-creek-treatment-ctr-for-eating-disorders-columbiana-al/220769"
  },
  {
    "address": "\n\n                                        Counseling and Therapy Services\n\n                    621 Old Stage Road\n                \nAuburn, Alabama 36830\n\nCall Timothy Birt\n\n(334) 239-4707\n\n\n",
    "url": "https://www.psychologytoday.com/us/therapists/counseling-and-therapy-services-auburn-al/210682"
  },
  {
    "address": "\n\n                                        Magic City Counseling, LLC\n\n                    500 Southland Drive, Ste 109\n                \nHoover, Alabama 35226\n\nCall Mrs. Chernell Bizzell-Barnett\n\n(205) 236-3208\n\n\n",
    "url": "https://www.psychologytoday.com/us/therapists/magic-city-counseling-llc-hoover-al/319947"
  },
  {
    "address": "\n\n                                        The Refinery Therapy Services \nHueytown, Alabama 35023\n\n\n(205) 461-1681\n\n\n",
    "url": "https://www.psychologytoday.com/us/therapists/tamara-blackledge-burr-hueytown-al/441588"
  },
  {
    "address": "\n\n                                        Professional Counseling Associates\n\n                    1920 Sparkman Drive NW\n                \n            \n                            Suite 6\nHuntsville, Alabama 35816\n\n\n(256) 279-9043\n\n\n",
    "url": "https://www.psychologytoday.com/us/therapists/danny-e-blanchard-huntsville-al/36772"
  },
  {
    "address": "\n\n                                        Alan Blotcky, PhD, LLC\n\n                    529 Beacon Parkway West\n                \n            \n                            Suite 107\nBirmingham, Alabama 35209\n\n\n(205) 509-4258\n\n\n",
    "url": "https://www.psychologytoday.com/us/therapists/alan-blotcky-phd-llc-birmingham-al/400983"
  },
  {
    "address": "\n\n                                        grayson and associates\n\n                    2200 Lakeshore Pkwy\n                \n            \n                            S- 150\nBirmingham, Alabama 35209\n\n\n(205) 502-2587\n\n\n",
    "url": "https://www.psychologytoday.com/us/therapists/karen-black-bluestein-birmingham-al/237554"
  },
  {
    "address": "\n\n                                        Blunt Counseling & Consulting\n\n                    2232 Cahaba Valley Drive\n                \n            \n                            Suite C\nBirmingham, Alabama 35242\n\n\n(205) 660-0511\n\n\n",
    "url": "https://www.psychologytoday.com/us/therapists/felicity-blunt-birmingham-al/286597"
  },
  {
    "address": "\n\n                                        Inspire Health Services LLC, Barry Bolin\n\n                    229 Broad Street\n                \nGadsden, Alabama 35901\n\nCall Barry Bolin\n\n(256) 304-8689\n\n\n",
    "url": "https://www.psychologytoday.com/us/therapists/inspire-health-services-llc-barry-bolin-gadsden-al/252014"
  },
  {
    "address": "\n\n                                        Healing Sounds Music Therapy\n\n                    1428 Weatherly Rd\n                \n            \n                            Suite 102\nHuntsville, Alabama 35803\n\n\n(256) 887-2350\n\n\n",
    "url": "https://www.psychologytoday.com/us/therapists/stephanie-bolton-huntsville-al/97452"
  },
  {
    "address": "\n\n                                        Reconciliation Counseling Services, LLC\n\n                    1087 Downtowner Blvd\n                \n            \n                            Suite A\nMobile, Alabama 36609\n\n\n(251) 333-2575\n\n\n",
    "url": "https://www.psychologytoday.com/us/therapists/steven-ray-booker-jr-mobile-al/280654"
  },
  {
    "address": "\n\n                                        Covenant Counseling and Consulting\n\n                    1230 Slaughter Rd\n                \n            \n                            Suite F\nMadison, Alabama 35758\n\n\n(256) 801-0509\n\n\n",
    "url": "https://www.psychologytoday.com/us/therapists/susan-borglum-madison-al/350870"
  },
  {
    "address": "\n\n\n                    39 Carol Villa Drive\n                \nMontgomery, Alabama 36109\n\n\n(334) 721-5327\n\n\n",
    "url": "https://www.psychologytoday.com/us/therapists/sam-boshell-montgomery-al/419813"
  },
  {
    "address": "\n\n                                        Peter P. Boyle\n\n                    2524 Valleydale Road\n                \n            \n                            Suite 100\nBirmingham, Alabama 35244\n\nCall Peter Boyle\n\n(205) 289-3510 x2\n\n\n",
    "url": "https://www.psychologytoday.com/us/therapists/peter-p-boyle-birmingham-al/343366"
  },
  {
    "address": "\n\n\n                    924 Montclair Road\n                \n            \n                            Suite 106\nBirmingham, Alabama 35213\n\n\n(205) 236-2916\n\n\n",
    "url": "https://www.psychologytoday.com/us/therapists/katasha-j-bozeman-birmingham-al/262274"
  },
  {
    "address": "\n\n\n                    300 Office Park Drive\n                \n            \n                            Suite 220\nMountain Brook, Alabama 35223\n\n\n(205) 538-3099\n\n\n",
    "url": "https://www.psychologytoday.com/us/therapists/jennifer-bradley-mountain-brook-al/448466"
  },
  {
    "address": "\n\n\n                    337 East Magnolia Ave\n                \n            \n                            Suite B\nAuburn, Alabama 36830\n\n\n(334) 339-7581\n\n\n",
    "url": "https://www.psychologytoday.com/us/therapists/sarah-j-bradley-auburn-al/383820"
  },
  {
    "address": "\n\n                                        A Family Matter\n\n                    416 North Seminary Street\n                \n            \n                            Suite 2100\nFlorence, Alabama 35630\n\n\n(256) 854-9958\n\n\n",
    "url": "https://www.psychologytoday.com/us/therapists/kent-r-brand-florence-al/43961"
  },
  {
    "address": "\n\n                                        Bray Counseling Services LLC\n\n                    2401 Main Street\n                \nDaphne, Alabama 36526\n\n\n(251) 214-0499\n\n\n",
    "url": "https://www.psychologytoday.com/us/therapists/cheryl-bray-daphne-al/77977"
  },
  {
    "address": "\n\n\n                    8450 Whispering Pines Road\n                \nDaphne, Alabama 36526\n\n\n(251) 422-8326\n\n\n",
    "url": "https://www.psychologytoday.com/us/therapists/marthanne-m-brewer-daphne-al/451930"
  },
  {
    "address": "\n\nMontgomery, Alabama 36117\n\nCall Dr. Lula Bridges\n\n(334) 403-4493\n\n\n",
    "url": "https://www.psychologytoday.com/us/therapists/innovative-sobriety-solutions-llc-montgomery-al/421111"
  },
  {
    "address": "\n\n                                        Brindley Group, LLC\n\n                    300 Vestavia Parkway\n                \n            \n                            Suite 1000\nVestavia Hills, Alabama 35216\n\nCall Kim Brindley\n\n(205) 683-2523\n\n\n",
    "url": "https://www.psychologytoday.com/us/therapists/brindley-group-llc-vestavia-hills-al/154935"
  },
  {
    "address": "\n\n                                        Auburn Psychology Group, LLC\n\n                    861-D N. Dean Rd.\n                \nAuburn, Alabama 36830\n\n\n(334) 715-0939\n\n\n",
    "url": "https://www.psychologytoday.com/us/therapists/rene-j-britt-auburn-al/37011"
  },
  {
    "address": "\n\n                                        Synergy Counseling Center\n\n                    7734 Madison Blvd\n                \n            \n                            Suite 122\nHuntsville, Alabama 35806\n\n\n(256) 290-0035\n\n\n",
    "url": "https://www.psychologytoday.com/us/therapists/don-g-brock-huntsville-al/123138"
  },
  {
    "address": "\n\n                                        Behavioral ONE\n\n                    2081 Columbiana Road\n                \nVestavia, Alabama 35216\n\n\n(205) 614-8539 x2102\n\n\n",
    "url": "https://www.psychologytoday.com/us/therapists/kelsey-brock-vestavia-al/362534"
  },
  {
    "address": "\n\n                                        Counseling Solutions of East Alabama\n\n                    2108 Executive Park Drive\n                \n            \n                            3 Minutes From The Auburn Mall\nOpelika, Alabama 36801\n\nCall Ms. Julia Brock\n\n(334) 231-8035\n\n\n",
    "url": "https://www.psychologytoday.com/us/therapists/counseling-solutions-of-east-alabama-opelika-al/180215"
  },
  {
    "address": "\n\n\n                    2305 Arlington Avenue South\n                \nBirmingham, Alabama 35205\n\n\n(205) 236-3937 x144\n\n\n",
    "url": "https://www.psychologytoday.com/us/therapists/jane-forsyth-brown-birmingham-al/354870"
  },
  {
    "address": "\n\n                                        Charlie Brown, NuView Counseling\n\n                    1120 Hillcrest Road, #2G\n                \nMobile, Alabama 36695\n\n\n(251) 401-3560\n\n\n",
    "url": "https://www.psychologytoday.com/us/therapists/charlie-brown-mobile-al/384286"
  },
  {
    "address": "\n\n                                        Jordan Hope Center\n\n                    701 Pratt Ave NW\n                \n            \n                            Suite 102\nHuntsville, Alabama 35801\n\n\n(855) 687-1066\n\n\n",
    "url": "https://www.psychologytoday.com/us/therapists/aaron-brown-huntsville-al/187501"
  },
  {
    "address": "\n\n                                        Freedom Professional Counseling\n\n                    3 Office Park Circle,\n                \n            \n                            Suite 105\nMountain Brook, Alabama 35223\n\n\n(251) 751-9205\n\n\n",
    "url": "https://www.psychologytoday.com/us/therapists/kerstin-brueck-mountain-brook-al/159923"
  },
  {
    "address": "\n\n                                        Heidi Bullock Counseling LLC\n\n                    # 3 Office Park Circle\n                \n            \n                            310\nMountain Brook, Alabama 35223\n\n\n(205) 417-4941\n\n\n",
    "url": "https://www.psychologytoday.com/us/therapists/heidi-lynn-bullock-mountain-brook-al/228460"
  },
  {
    "address": "\n\n                                        Amy Burke Counseling, LLC\n\n                    2127 14th Ave S\n                \nBirmingham, Alabama 35205\n\n\n(205) 598-7843\n\n\n",
    "url": "https://www.psychologytoday.com/us/therapists/amy-lyons-burke-birmingham-al/414136"
  },
  {
    "address": "\n\n                                        Comprehensive MedPsych Systems\n\n                    1110 Montlimar Place\n                \n            \n                            Suite 500\nMobile, Alabama 36609\n\n\n(251) 333-2287\n\n\n",
    "url": "https://www.psychologytoday.com/us/psychiatrists/amy-burkhardt-mobile-al/365242"
  },
  {
    "address": "\n\n                                        Behavioral Sciences of Alabama\n\n                    810 Shoney Dr SW #120\n                \nHuntsville, Alabama 35801\n\n\n(256) 883-3231\n\n\n",
    "url": "https://www.psychologytoday.com/us/therapists/lindsay-harrison-burleson-huntsville-al/286976"
  },
  {
    "address": "\n\n                                        Professional Counseling Associates\nDaphne, Alabama 36526\n\n\n(251) 317-0014\n\n\n",
    "url": "https://www.psychologytoday.com/us/therapists/kay-bush-sorrells-daphne-al/148395"
  },
  {
    "address": "\n\n                                        Jay Byham Counseling\n\n                    111 Longwood Drive SW\n                \nHuntsville, Alabama 35801\n\nCall Mr. Jay Byham\n\n(256) 474-0898\n\n\n",
    "url": "https://www.psychologytoday.com/us/therapists/jay-byham-counseling-huntsville-al/234179"
  },
  {
    "address": "\n\n                                        BB&H Wellness Services, LLC\n\n                    1785 Taliaferro Trail\n                \n            \n                            Suite B\nMontgomery, Alabama 36117\n\nCall Mr. Craig Bynum\n\n(334) 676-2368\n\n\n",
    "url": "https://www.psychologytoday.com/us/therapists/bbh-wellness-services-llc-montgomery-al/176748"
  },
  {
    "address": "\n\n                                        Liz Byrne, LPC\n\n                    915 Willowbrook Drive\n                \n            \n                            Suite D\nHuntsville, Alabama 35803\n\nCall Ms. Liz Byrne\n\n(256) 203-9252\n\n\n",
    "url": "https://www.psychologytoday.com/us/therapists/liz-byrne-lpc-huntsville-al/263667"
  },
  {
    "address": "\n\n                                        Anchor of Hope Counseling\n\n                    39 Carol Villa Drive\n                \n            \n                            A\nMontgomery, Alabama 36109\n\n\n(334) 564-8657\n\n\n",
    "url": "https://www.psychologytoday.com/us/therapists/madalyn-caldwell-montgomery-al/397747"
  },
  {
    "address": "\n\n                                        Village Counseling and Consulting, LLC\n\n                    215 Walnut St\n                \n            \n                            Ste 2\nGadsden, Alabama 35901\n\nCall Mrs. Dana Calhoun\n\n(256) 829-2689\n\n\n",
    "url": "https://www.psychologytoday.com/us/therapists/village-counseling-and-consulting-llc-gadsden-al/371082"
  },
  {
    "address": "\n\n                                        Stephanie Calhoun, LPC\n\n                    400 Fairhope Avenue\n                \n            \n                            Suite 2G\nFairhope, Alabama 36532\n\nCall Stephanie Calhoun\n\n(251) 581-7454\n\n\n",
    "url": "https://www.psychologytoday.com/us/therapists/stephanie-calhoun-lpc-fairhope-al/234251"
  },
  {
    "address": "\n\n                                        Behavioral Sciences of Alabama\n\n                    810 Shoney Drive\n                \n            \n                            Suite 120\nHuntsville, Alabama 35801\n\n\n(256) 858-7588\n\n\n",
    "url": "https://www.psychologytoday.com/us/therapists/haley-michelle-callahan-huntsville-al/419798"
  },
  {
    "address": "\n\n\n                    4092 Memorial Parkway Southwest\n                \nHuntsville, Alabama 35802\n\n\n(938) 444-8837\n\n\n",
    "url": "https://www.psychologytoday.com/us/therapists/iantha-calloway-huntsville-al/430960"
  },
  {
    "address": "\n\n\n                    402 Office Park Drive\n                \n            \n                            Suite 300B\nBirmingham, Alabama 35223\n\n\n(205) 236-9945\n\n\n",
    "url": "https://www.psychologytoday.com/us/therapists/adam-calvert-birmingham-al/428332"
  },
  {
    "address": "\n\n\n                    1229 3rd Avenue North\n                \nBirmingham, Alabama 35203\n\nCall Mrs. April Calvin\n\n(205) 619-6260\n\n\n",
    "url": "https://www.psychologytoday.com/us/therapists/in-touch-counseling-agency-birmingham-al/453186"
  },
  {
    "address": "\n\n\n                    2909 Crescent Avenue\n                \nBirmingham, Alabama 35209\n\n\n(205) 703-2145\n\n\n",
    "url": "https://www.psychologytoday.com/us/therapists/mary-ellen-capps-birmingham-al/171008"
  },
  {
    "address": "\n\n\n                    300 Vestavia Parkway\n                \n            \n                            Suite 3900\nVestavia, Alabama 35216\n\n\n(205) 378-7899\n\n\n",
    "url": "https://www.psychologytoday.com/us/therapists/chris-r-cargile-vestavia-al/427256"
  },
  {
    "address": "\n\n\n                    5905 Airport Boulevard\n                \n            \n                            Suite D\nMobile, Alabama 36608\n\n\n(251) 317-3214\n\n\n",
    "url": "https://www.psychologytoday.com/us/therapists/deborah-p-carmichael-mobile-al/238335"
  },
  {
    "address": "\n\n                                        Clarity Health LLC\n\n                    2054 Dauphin Street\n                \nMobile, Alabama 36606\n\n\n(251) 732-2605\n\n\n",
    "url": "https://www.psychologytoday.com/us/therapists/jack-christopher-carney-mobile-al/388382"
  },
  {
    "address": "\n\nHoover, Alabama 35216\n\n\n(844) 239-6511\n\n\n",
    "url": "https://www.psychologytoday.com/us/therapists/bre-carr-hoover-al/406289"
  },
  {
    "address": "\n\n                                        Impact Family Counseling\n\n                    701 Montgomery Hwy\n                \n            \n                            Suite 202\nVestavia Hills, Alabama 35216\n\nCall Mr. George Casey\n\n(205) 289-8679\n\n\n",
    "url": "https://www.psychologytoday.com/us/therapists/impact-family-counseling-vestavia-hills-al/65733"
  },
  {
    "address": "\n\n                                        Garrett Counseling\n\n                    605 - A Medical Center Parkway\n                \nBoaz, Alabama 35957\n\n\n(256) 857-5983\n\n\n",
    "url": "https://www.psychologytoday.com/us/therapists/ginger-caudell-boaz-al/389086"
  },
  {
    "address": "\n\n                                        TC Counseling & Consulting Services, LLC\n\n                    13 Office Park Circle, Suite 19\n                \nMountain Brook, Alabama 35223\n\nCall Mrs. Tammy Cauthen\n\n(205) 377-5537\n\n\n",
    "url": "https://www.psychologytoday.com/us/therapists/tc-counseling-consulting-tammy-cauthen-mountain-brook-al/114853"
  },
  {
    "address": "\n\n\n                    2100A southbridge parkway\n                \n            \n                            suite 650\nBirmingham, Alabama 35209\n\nCall Ms. Dominique Cecil\n\n(205) 236-9136\n\n\n",
    "url": "https://www.psychologytoday.com/us/therapists/yellow-bird-counseling-llc-birmingham-al/424683"
  },
  {
    "address": "\n\n                                        Optimize Counseling and Therapy\n\n                    300 Office Park Dr, Ste 220\n                \nMountain Brook, Alabama 35223\n\n\n(205) 236-2106\n\n\n",
    "url": "https://www.psychologytoday.com/us/therapists/david-p-cecil-optimize-counseling-and-therapy-mountain-brook-al/311571"
  },
  {
    "address": "\n\n                                        Samaritan Counseling Centers of Birmingham\n\n                    300 Cahaba Park Circle\n                \n            \n                            Suite 202\nBirmingham, Alabama 35242\n\nCall Samaritan Centers\n\n(205) 618-8721\n\n\n",
    "url": "https://www.psychologytoday.com/us/therapists/samaritan-counseling-centers-of-birmingham-birmingham-al/182666"
  },
  {
    "address": "\n\n                                        A New Perspective Counseling, LLC\n\n                    2835 Zelda Rd\n                \n            \n                            Suite 10\nMontgomery, Alabama 36106\n\nCall Mrs. Courtney Cephas-Bass\n\n(334) 431-3674\n\n\n",
    "url": "https://www.psychologytoday.com/us/therapists/a-new-perspective-counseling-llc-montgomery-al/305089"
  },
  {
    "address": "\n\n                                        Lori L. Chancy Counseling Services, LLC\n\n                    101 Medical Drive\n                \nDothan, Alabama 36305\n\n\n(334) 370-0061\n\n\n",
    "url": "https://www.psychologytoday.com/us/therapists/lori-lynn-chancy-dothan-al/241067"
  },
  {
    "address": "\n\n\n                    1856 Navco Road\n                \n            \n                            Lake-Chastang Camellia Preserve\nMobile, Alabama 36605\n\n\n(251) 270-1085\n\n\n",
    "url": "https://www.psychologytoday.com/us/therapists/davey-james-chastang-mobile-al/157429"
  },
  {
    "address": "\n\n                                        Chavis Counseling Service, LLC\n\n                    600 Interstate Park Drive \n                \n            \n                            Suite 609\nMontgomery, Alabama 36109\n\nCall Mr. Thomas Chavis\n\n(334) 454-4366\n\n\n",
    "url": "https://www.psychologytoday.com/us/therapists/chavis-counseling-service-llc-montgomery-al/367109"
  },
  {
    "address": "\n\n                                        Cornerstone Counseling Center\n\n                    2102 Franklin Street\n                \nHuntsville, Alabama 35801\n\n\n(256) 952-7897\n\n\n",
    "url": "https://www.psychologytoday.com/us/therapists/sarah-cholevik-huntsville-al/104145"
  },
  {
    "address": "\n\n                                        Brenda Chynoweth LPC, LLC\n\n                    475 Providence Main Street\n                \n            \n                            Suite 303J\nHuntsville, Alabama 35806\n\n\n(256) 829-2310\n\n\n",
    "url": "https://www.psychologytoday.com/us/therapists/brenda-c-chynoweth-huntsville-al/269140"
  },
  {
    "address": "\n\n\n                    Samaritan Counseling Center\n                \n            \n                            PO Box 380305\nBirmingham, Alabama 35238\n\n\n(205) 519-3586\n\n\n",
    "url": "https://www.psychologytoday.com/us/therapists/marcelle-marie-ciampa-birmingham-al/446176"
  },
  {
    "address": "\n\n                                        TurningPoint Counseling Services\n\n                    7734 Madison Blvd\n                \n            \n                            Suite 101\nHuntsville, Alabama 35806\n\n\n(256) 573-1087\n\n\n",
    "url": "https://www.psychologytoday.com/us/therapists/james-w-bill-clark-huntsville-al/263375"
  },
  {
    "address": "\n\n\n                    1623 Forest Avenue\n                \nMontgomery, Alabama 36106\n\n\n(334) 218-5860\n\n\n",
    "url": "https://www.psychologytoday.com/us/therapists/alicia-m-claybon-montgomery-al/227350"
  },
  {
    "address": "\n\n                                        Psychotherapy/Clinical Services\n\n                    2622 Jordan Lane\n                \nHuntsville, Alabama 35816\n\n\n(256) 297-2643\n\n\n",
    "url": "https://www.psychologytoday.com/us/therapists/esophia-clayborn-huntsville-al/200944"
  },
  {
    "address": "\n\n                                        Pesek Counseling Services\n\n                    277 Village Parkway\n                \nHelena, Alabama 35080\n\n\n(205) 774-6164\n\n\n",
    "url": "https://www.psychologytoday.com/us/therapists/brittany-cockrum-helena-al/336514"
  },
  {
    "address": "\n\n                                        Thoughtful Journey Counseling\n\n                    409 N Court Street\n                \n            \n                            Suite #203\nFlorence, Alabama 35630\n\n\n(256) 361-1314\n\n\n",
    "url": "https://www.psychologytoday.com/us/therapists/celeste-coffman-florence-al/205478"
  },
  {
    "address": "\n\n\n                    255 Grant Street Southeast Suite 303\n                \nDecatur, Alabama 35601\n\n\n(256) 973-9848\n\n\n",
    "url": "https://www.psychologytoday.com/us/therapists/sherri-cohen-decatur-al/417588"
  },
  {
    "address": "\n\n                                        The Centre\nDaphne, Alabama 36526\n\n\n(251) 732-2014\n\n\n",
    "url": "https://www.psychologytoday.com/us/therapists/robert-e-colclough-daphne-al/114454"
  },
  {
    "address": "\n\n                                        Collins Counseling & Associates, P.C.\n\n                    1340 Sledge Drive\n                \nMobile, Alabama 36606\n\n\n(251) 589-6896\n\n\n",
    "url": "https://www.psychologytoday.com/us/therapists/mary-lee-collins-mobile-al/146493"
  },
  {
    "address": "\n\nDothan, Alabama 36301\n\n\n(334) 500-4366\n\n\n",
    "url": "https://www.psychologytoday.com/us/therapists/jennifer-e-compton-dothan-al/455058"
  },
  {
    "address": "\n\n\n                    85 Bagby Drive\n                \n            \n                            Suite 108\nBirmingham, Alabama 35209\n\n\n(205) 572-9886\n\n\n",
    "url": "https://www.psychologytoday.com/us/therapists/tori-kate-conner-hearn-birmingham-al/423996"
  },
  {
    "address": "\n\n\n                    420 28th Avenue\n                \n            \n                            Suite 100\nTuscaloosa, Alabama 35401\n\n\n(205) 624-0172\n\n\n",
    "url": "https://www.psychologytoday.com/us/therapists/jonathan-alan-cook-tuscaloosa-al/240224"
  },
  {
    "address": "\n\n                                        Elizabeth C. Cook, LPC\n\n                    607 McCullough Avenue Northeast\n                \nHuntsville, Alabama 35801\n\n\n(256) 827-7428\n\n\n",
    "url": "https://www.psychologytoday.com/us/therapists/elizabeth-cook-huntsville-al/389229"
  },
  {
    "address": "\n\nHuntsville, Alabama 35824\n\n\n(938) 999-9554\n\n\n",
    "url": "https://www.psychologytoday.com/us/therapists/tobea-cook-lpc-huntsville-al/447059"
  },
  {
    "address": "\n\n                                        Lotus Counseling Services\n\n                    2011 9th Ave S\n                \n            \n                            200B\nBirmingham, Alabama 35205\n\n\n(205) 236-7298 x1\n\n\n",
    "url": "https://www.psychologytoday.com/us/therapists/adrienne-s-cooper-birmingham-al/306561"
  },
  {
    "address": "\n\n                                        Copeland Counseling & Consulting\n\n                    300 Office Park Drive\n                \n            \n                            Suite 220\nBirmingham, Alabama 35223\n\n\n(205) 286-3377\n\n\n",
    "url": "https://www.psychologytoday.com/us/therapists/rachel-copeland-birmingham-al/291514"
  },
  {
    "address": "\n\n                                        Cageless Birds Counseling\n\n                    400 Vestavia Parkway, Suite 135\n                \nVestavia Hills, Alabama 35216\n\n\n(205) 512-9071\n\n\n",
    "url": "https://www.psychologytoday.com/us/therapists/laura-k-cordova-vestavia-hills-al/327726"
  },
  {
    "address": "\n\n                                        Ozark Counseling and Testing Center\n\n                    1518 East Andrews Avenue\n                \nOzark, Alabama 36360\n\nCall Mrs. Madeliine Cornett\n\n(334) 758-9396\n\n\n",
    "url": "https://www.psychologytoday.com/us/therapists/ozark-counseling-and-testing-center-ozark-al/234329"
  },
  {
    "address": "\n\n\n                    1950 Rainbow Drive\n                \nGadsden, Alabama 35901\n\n\n(256) 305-4817\n\n\n",
    "url": "https://www.psychologytoday.com/us/therapists/carol-costner-gadsden-al/417169"
  },
  {
    "address": "\n\n\n                    1878 Jeff Road\n                \n            \n                            Suite J\nHuntsville, Alabama 35806\n\n\n(256) 384-3203\n\n\n",
    "url": "https://www.psychologytoday.com/us/therapists/kelly-cothran-huntsville-al/73642"
  },
  {
    "address": "\n\n                                        Couch Counseling, PC\n\n                    1307 Christine Ave\n                \nAnniston, Alabama 36207\n\nCall Mrs. Edith Couch\n\n(256) 251-5568\n\n\n",
    "url": "https://www.psychologytoday.com/us/therapists/couch-counseling-pc-anniston-al/280643"
  },
  {
    "address": "\n\n                                        Elite Center for Change\n\n                    496 Hwy 67 South\n                \n            \n                            Suite A\nDecatur, Alabama 35601\n\n\n(256) 384-8679\n\n\n",
    "url": "https://www.psychologytoday.com/us/therapists/michelle-couey-decatur-al/256947"
  },
  {
    "address": "\n\n                                        Eagle Consulting/Counseling Division\n\n                    475 Providence Main St\n                \n            \n                            Suite 401\nHuntsville, Alabama 35806\n\nCall Eagle Consulting Counseling Division\n\n(256) 693-8476\n\n\n",
    "url": "https://www.psychologytoday.com/us/therapists/eagle-consultingcounseling-division-huntsville-al/292853"
  },
  {
    "address": "\n\n                                        Encounter Counseling Center, LLC\nDaphne, Alabama 36526\n\n\n(251) 250-0814\n\n\n",
    "url": "https://www.psychologytoday.com/us/therapists/michelle-counts-daphne-al/394988"
  },
  {
    "address": "\n\n\n                    191 Katherine Ave.\n                \nOzark, Alabama 36360\n\n\n(334) 694-2257\n\n\n",
    "url": "https://www.psychologytoday.com/us/therapists/theron-covin-ozark-al/38435"
  },
  {
    "address": "\n\n                                        Thrive Counseling and Trauma Therapy\n\n                    1034 23rd Street South \n                \n            \n                            Suite 102\nBirmingham, Alabama 35205\n\n\n(205) 519-3740\n\n\n",
    "url": "https://www.psychologytoday.com/us/therapists/meosha-cox-birmingham-al/412732"
  },
  {
    "address": "\n\n                                        Kathryn M. Cox, LPC\n\n                    1408 5th Ave, SE\n                \n            \n                            Suite 4\nDecatur, Alabama 35601\n\n\n(256) 384-4027\n\n\n",
    "url": "https://www.psychologytoday.com/us/therapists/kathryn-m-cox-decatur-al/126839"
  },
  {
    "address": "\n\n                                        Finding Fortitude Counseling\n\n                    215 Walnut Street\n                \n            \n                            Suite 1\nGadsden, Alabama 35901\n\n\n(256) 664-4573\n\n\n",
    "url": "https://www.psychologytoday.com/us/therapists/crystal-fulghum-crawford-gadsden-al/174573"
  },
  {
    "address": "\n\n                                        Grace Counseling & Consultation Services, LLC\n\n                    650 Sun Temple Dr\n                \nMadison, Alabama 35758\n\n\n(256) 530-7433\n\n\n",
    "url": "https://www.psychologytoday.com/us/therapists/grace-crawford-madison-al/317207"
  },
  {
    "address": "\n\n                                        Tombigbee Outreach\n\n                    105 US Hwy 80 East, PO Box 890\n                \nDemopolis, Alabama 36732\n\nCall Mrs. Kate Crawford\n\n(334) 319-9937\n\n\n",
    "url": "https://www.psychologytoday.com/us/treatment-rehab/tombigbee-outreach-demopolis-al/356967"
  },
  {
    "address": "\n\n                                        Covenant Counseling & Consulting\n\n                    1230 Slaughter Rd\n                \n            \n                            Madison\nMadison, Alabama 35758\n\n\n(256) 743-6543\n\n\n",
    "url": "https://www.psychologytoday.com/us/therapists/lyn-crawford-madison-al/400243"
  },
  {
    "address": "\n\n                                        Michelle Crumbly LPC, LLC\n\n                    621 Old Stage Road\n                \nAuburn, Alabama 36830\n\n\n(334) 219-3763\n\n\n",
    "url": "https://www.psychologytoday.com/us/therapists/michelle-crumbly-auburn-al/143583"
  },
  {
    "address": "\n\n                                        Birmingham Counseling and Wellness\n\n                    3250 Independence Drive\n                \n            \n                            Suite 200\nHomewood, Alabama 35209\n\nCall Gwendolyn Crumpton\n\n(205) 578-0550\n\n\n",
    "url": "https://www.psychologytoday.com/us/therapists/birmingham-counseling-and-wellness-homewood-al/273205"
  },
  {
    "address": "\n\n                                        USA Psychological Clinic\n\n                    75 S University Blvd\n                \n            \n                            Ucom 2000\nMobile, Alabama 36688\n\n\n(251) 234-6521\n\n\n",
    "url": "https://www.psychologytoday.com/us/therapists/joseph-currier-mobile-al/192471"
  },
  {
    "address": "\n\n                                        Ashton Dale Counseling Services LLC\n\n                    21333 State Highway 181\n                \n            \n                            Suite E\nFairhope, Alabama 36532\n\n\n(251) 929-4955\n\n\n",
    "url": "https://www.psychologytoday.com/us/therapists/ashton-e-dale-fairhope-al/241916"
  },
  {
    "address": "\n\n                                        Auburn Psychology Group, LLC\n\n                    861-D North Dean Road\n                \nAuburn, Alabama 36830\n\n\n(334) 392-4599\n\n\n",
    "url": "https://www.psychologytoday.com/us/therapists/jennifer-b-daniels-auburn-al/119262"
  },
  {
    "address": "\n\n                                        Amy Daniels LPC, Inc.\n\n                    5821 Rangeline Rd\n                \n            \n                            Suite 214\nTheodore, Alabama 36582\n\nCall Amy Daniels\n\n(251) 366-1710\n\n\n",
    "url": "https://www.psychologytoday.com/us/therapists/amy-daniels-lpc-inc-theodore-al/239156"
  },
  {
    "address": "\n\n                                        Pitts & Associates\n\n                    601 Beacon Parkway West\n                \n            \n                            Suite 201\nBirmingham, Alabama 35209\n\n\n(205) 282-9259\n\n\n",
    "url": "https://www.psychologytoday.com/us/therapists/lorne-dann-birmingham-al/53380"
  },
  {
    "address": "\n\n                                        Danne-Wilson Counseling\n\n                    1957 Hoover Ct\n                \n            \n                            Suite 218\nBirmingham, Alabama 35226\n\nCall Mrs. Tomekia Danne-Wilson\n\n(205) 994-8140\n\n\n",
    "url": "https://www.psychologytoday.com/us/therapists/danne-wilson-counseling-birmingham-al/316141"
  },
  {
    "address": "\n\n                                        Daugette Family Counseling\n\n                    1110 Hillcrest Road\n                \n            \n                            1B\nMobile, Alabama 36695\n\nCall Mrs. Whitney Daugette\n\n(251) 387-7760\n\n\n",
    "url": "https://www.psychologytoday.com/us/therapists/daugette-family-health-services-llc-mobile-al/361303"
  },
  {
    "address": "\n\n                                        Addiction Specialists LLC\n\n                    175 Aliant Parkway\n                \nAlexander City, Alabama 35011\n\n\n(205) 289-5087\n\n\n",
    "url": "https://www.psychologytoday.com/us/therapists/tom-davis-alexander-city-al/322701"
  },
  {
    "address": "\n\n                                        Broken To Art Counseling, LLC\n\n                    2100 Southbridge Parkway\n                \n            \n                            Suite 650\nBirmingham, Alabama 35209\n\nCall Ms. Lasheena Davis\n\n(205) 224-0690\n\n\n",
    "url": "https://www.psychologytoday.com/us/therapists/broken-to-art-counseling-llc-birmingham-al/392574"
  },
  {
    "address": "\n\n                                        LPC Services, LLC\n\n                    605 Bel Air Blvd\n                \n            \n                            Suite 10\nMobile, Alabama 36606\n\n\n(251) 272-3722\n\n\n",
    "url": "https://www.psychologytoday.com/us/therapists/veronica-davis-mobile-al/235747"
  },
  {
    "address": "\n\n                                        Alexander Counseling Services\n\n                    300 Office Park Dr\n                \n            \n                            Suite 220\nMountain Brook, Alabama 35223\n\n\n(205) 538-3099\n\n\n",
    "url": "https://www.psychologytoday.com/us/therapists/stephanie-davis-mountain-brook-al/357024"
  },
  {
    "address": "\n\n                                        Journey Counseling & Consulting, LLC\n\n                    2820 Columbiana Rd\n                \n            \n                            Suite 210K\nVestavia Hills, Alabama 35216\n\n\n(205) 509-2985\n\n\n",
    "url": "https://www.psychologytoday.com/us/therapists/ashley-c-davis-vestavia-hills-al/376109"
  },
  {
    "address": "\n\n                                        I C.A.R.E. Wellness Services\nBirmingham, Alabama 35208\n\nCall Dr. Griena Davis\n\n(205) 236-6774\n\n\n",
    "url": "https://www.psychologytoday.com/us/therapists/i-care-wellness-services-llc-birmingham-al/331071"
  },
  {
    "address": "\n\n\n                    273 Azalea Road\n                \n            \n                            Suite 2-413\nMobile, Alabama 36609\n\n\n(251) 241-4167\n\n\n",
    "url": "https://www.psychologytoday.com/us/therapists/john-william-davis-mobile-al/193160"
  },
  {
    "address": "\n\n                                        Jill Dean, Ed.S, L.P.C. Counseling Services\n\n                    3447 Pelham Parkway\n                \nPelham, Alabama 35124\n\n\n(205) 703-2815\n\n\n",
    "url": "https://www.psychologytoday.com/us/therapists/jill-dean-pelham-al/178191"
  },
  {
    "address": "\n\n\n                    720 Energy Center Boulevard\n                \n            \n                            Suite 502\nNorthport, Alabama 35473\n\n\n(205) 409-0254\n\n\n",
    "url": "https://www.psychologytoday.com/us/therapists/marian-tina-deloach-northport-al/435841"
  },
  {
    "address": "\n\n                                        Jacqueline Dillon DeMarco, Ph.D., P.C.\n\n                    2917 Central Ave\n                \n            \n                            Suite 305\nHomewood, Alabama 35209\n\n\n(205) 718-5433\n\n\n",
    "url": "https://www.psychologytoday.com/us/therapists/jacqueline-dillon-demarco-homewood-al/95111"
  },
  {
    "address": "\n\n                                        Elk River Treatment Program\nHuntsville, Alabama 35816\n\nCall Kathy DeMellier\n\n(855) 770-7709\n\n\n",
    "url": "https://www.psychologytoday.com/us/treatment-rehab/elk-river-treatment-program-huntsville-al/90816"
  },
  {
    "address": "\n\n                                        Dennis Counseling\n\n                    2750 Pelham Rd S\n                \n            \n                            Suite 4\nAnniston, Alabama 36206\n\n\n(256) 472-2160\n\n\n",
    "url": "https://www.psychologytoday.com/us/therapists/tashua-berry-dennis-anniston-al/284095"
  },
  {
    "address": "\n\n                                        Ackerson & Associates\n\n                    400 Vestavia Parkway\n                \n            \n                            Suite 130\nVestavia Hills, Alabama 35216\n\n\n(205) 352-4180\n\n\n",
    "url": "https://www.psychologytoday.com/us/therapists/drake-denton-vestavia-hills-al/165048"
  },
  {
    "address": "\n\n\n                    116 Jefferson Street S\n                \n            \n                            Suite 208\nHuntsville, Alabama 35801\n\n\n(256) 952-4827\n\n\n",
    "url": "https://www.psychologytoday.com/us/therapists/chris-depew-huntsville-al/208439"
  },
  {
    "address": "\n\n                                        Auburn Psychology Group\n\n                    861-D N Dean Rd\n                \nAuburn, Alabama 36830\n\n\n(334) 721-1430\n\n\n",
    "url": "https://www.psychologytoday.com/us/therapists/michelle-k-deramus-auburn-al/296223"
  },
  {
    "address": "\n\n                                        Longwood Psychological Center\n\n                    111 Longwood Drive SW\n                \nHuntsville, Alabama 35801\n\n\n(256) 645-8832\n\n\n",
    "url": "https://www.psychologytoday.com/us/therapists/james-p-desta-huntsville-al/308202"
  },
  {
    "address": "\n\n                                        Alabama Psychiatry and Counseling\n\n                    2016 Stonegate Trail\n                \n            \n                            Suite 112\nVestavia Hills, Alabama 35242\n\n\n(205) 209-4450\n\n\n",
    "url": "https://www.psychologytoday.com/us/therapists/jackie-moore-devine-vestavia-hills-al/233442"
  },
  {
    "address": "\n\n                                        Huntsville Neuropsychiatric Services\n\n                    185 Whitesport Drive\n                \n            \n                            Suite 5\nHuntsville, Alabama 35801\n\n\n(256) 401-7741\n\n\n",
    "url": "https://www.psychologytoday.com/us/psychiatrists/gagan-dhaliwal-huntsville-al/290104"
  },
  {
    "address": "\n\n                                        Prism Counseling Services, LLC\nEnterprise, Alabama 36330\n\n\n(334) 232-8606\n\n\n",
    "url": "https://www.psychologytoday.com/us/therapists/amanda-dickey-enterprise-al/384252"
  },
  {
    "address": "\n\n\n                    2109 Darlington St.\n                \nHoover, Alabama 35226\n\n\n(205) 588-1454\n\n\n",
    "url": "https://www.psychologytoday.com/us/therapists/emily-d-dickinson-hoover-al/105159"
  },
  {
    "address": "\n\n                                        Premier Psychiatry, P.C.\n\n                    4 Office Park Circle\n                \n            \n                            # 305\nMountain Brook, Alabama 35223\n\nCall Dr. James Dilday\n\n(205) 686-4813\n\n\n",
    "url": "https://www.psychologytoday.com/us/psychiatrists/premier-psychiatry-pc-mountain-brook-al/237721"
  },
  {
    "address": "\n\n\n                    4800 Whitesport Circle, Suite 2\n                \nHuntsville, Alabama 35801\n\n\n(256) 607-9239\n\n\n",
    "url": "https://www.psychologytoday.com/us/therapists/louisa-n-dileone-huntsville-al/351997"
  },
  {
    "address": "\n\n                                        Hurley Counseling, LLC\n\n                    1900 Dauphin Street\n                \nMobile, Alabama 36606\n\n\n(251) 243-0799\n\n\n",
    "url": "https://www.psychologytoday.com/us/therapists/dawn-m-diquattro-mobile-al/330640"
  },
  {
    "address": "\n\n                                        Individual & Couples Counseling\n\n                    1111 East I-65 Service Rd South\n                \n            \n                            Suite A\nMobile, Alabama 36606\n\nCall Mr. Don Dockery\n\n(251) 599-7339\n\n\n",
    "url": "https://www.psychologytoday.com/us/therapists/individual-couples-counseling-mobile-al/69002"
  },
  {
    "address": "\n\n                                        Robbie Dodson Counseling \n\n                    5151 Research Dr \n                \n            \n                            Suite B\nHuntsville, Alabama 35805\n\n\n(256) 305-1104\n\n\n",
    "url": "https://www.psychologytoday.com/us/therapists/robbie-m-dodson-huntsville-al/304700"
  },
  {
    "address": "\n\n                                        Deborah Dorris Counseling LLC\n\n                    4252 Carmichael Road\n                \nMontgomery, Alabama 36106\n\n\n(334) 781-7075\n\n\n",
    "url": "https://www.psychologytoday.com/us/therapists/deborah-dorris-montgomery-al/284857"
  },
  {
    "address": "\n\n                                        Douglas Counseling Services, LLC\n\n                    2025 3rd Avenue North\n                \n            \n                            Suite 204\nBirmingham, Alabama 35203\n\n\n(205) 610-8140\n\n\n",
    "url": "https://www.psychologytoday.com/us/therapists/ronald-e-douglas-birmingham-al/104601"
  },
  {
    "address": "\n\n                                        Living Life Counseling Center\n\n                    540 Hughes Road\n                \n            \n                            Suite 10a\nMadison, Alabama 35758\n\nCall Dr. Denise Draa\n\n(256) 304-8295\n\n\n",
    "url": "https://www.psychologytoday.com/us/therapists/living-life-counseling-center-madison-al/306046"
  },
  {
    "address": "\n\n                                        Collins Counseling & Associates, P.C.\n\n                    1340 Sledge Drive\n                \nMobile, Alabama 36606\n\n\n(251) 237-4505\n\n\n",
    "url": "https://www.psychologytoday.com/us/therapists/kevin-j-dudeck-mobile-al/331002"
  },
  {
    "address": "\n\n                                        Cahaba Therapy and Wellness\n\n                    2100 Southbridge Pkwy\n                \n            \n                            Suite 650\nBirmingham, Alabama 35209\n\n\n(205) 881-5117\n\n\n",
    "url": "https://www.psychologytoday.com/us/therapists/kelly-duke-birmingham-al/387451"
  },
  {
    "address": "\n\n                                        Sparrow Counseling, LLC\n\n                    2917 Central Ave\n                \n            \n                            Suite 305\nBirmingham, Alabama 35209\n\n\n(205) 483-2170\n\n\n",
    "url": "https://www.psychologytoday.com/us/therapists/sara-dungan-birmingham-al/274447"
  },
  {
    "address": "\n\n                                        Rocket City Counselor\n\n                    120 Holmes Ave NW\n                \n            \n                            Ste 400\nHuntsville, Alabama 35801\n\n\n(256) 419-5180\n\n\n",
    "url": "https://www.psychologytoday.com/us/therapists/christine-dunn-huntsville-al/397418"
  },
  {
    "address": "\n\n                                        Psychological Assessment Center, LLC\n\n                    3320 Skyway Drive\n                \n            \n                            Suite 802\nOpelika, Alabama 36801\n\n\n(334) 528-0306\n\n\n",
    "url": "https://www.psychologytoday.com/us/therapists/polly-dunn-opelika-al/350887"
  },
  {
    "address": "\n\n                                        Lighthouse Clinical Social Work, L.L.C.\n\n                    953 Jeff Road NW\n                \nHuntsville, Alabama 35806\n\n\n(256) 579-1968\n\n\n",
    "url": "https://www.psychologytoday.com/us/therapists/debbie-k-duquette-huntsville-al/383844"
  },
  {
    "address": "\n\n                                        Mind, Body, & Heart Wellness Clinic\n\n                    100 Century Park South\n                \n            \n                            Suite 102\nBirmingham, Alabama 35226\n\n\n(334) 339-7195\n\n\n",
    "url": "https://www.psychologytoday.com/us/therapists/luke-durham-birmingham-al/328439"
  },
  {
    "address": "\n\n                                        Michelle Edwards, LPC\n\n                    3762 Moffett Road\n                \n            \n                            Suite A\nMobile, Alabama 36618\n\nCall Mrs. Michelle Edwards\n\n(251) 207-4021\n\n\n",
    "url": "https://www.psychologytoday.com/us/therapists/michelle-edwards-lpc-mobile-al/234106"
  },
  {
    "address": "\n\n                                        East Bay Psychiatry & Associates\n\n                    761 B Middle St\n                \nFairhope, Alabama 36532\n\n\n(251) 580-6652\n\n\n",
    "url": "https://www.psychologytoday.com/us/therapists/walter-l-elam-fairhope-al/282739"
  },
  {
    "address": "\n\n\n                    613 Gulf Shores Parkway\n                \n            \n                            204\nGulf Shores, Alabama 36542\n\n\n(334) 203-2039\n\n\n",
    "url": "https://www.psychologytoday.com/us/therapists/nanette-f-elkins-gulf-shores-al/354766"
  },
  {
    "address": "\n\n\n                    7085 Sydney Curve\n                \nMontgomery, Alabama 36117\n\n\n(334) 459-9451\n\n\n",
    "url": "https://www.psychologytoday.com/us/therapists/lisa-elliott-montgomery-al/422234"
  },
  {
    "address": "\n\n                                        Practice-Works\n\n                    3613 6th Avenue South\n                \nBirmingham, Alabama 35222\n\n\n(205) 708-3345\n\n\n",
    "url": "https://www.psychologytoday.com/us/therapists/linda-ellis-birmingham-al/321975"
  },
  {
    "address": "\n\n\n                    9 Office Park Circle\n                \n            \n                            Suite 106\nBirmingham, Alabama 35223\n\nCall Mrs. Kathryn Ely\n\n(205) 526-3674\n\n\n",
    "url": "https://www.psychologytoday.com/us/therapists/empower-counseling-llc-birmingham-al/444145"
  },
  {
    "address": "\n\n                                        Journey to Hope, LLC\n\n                    8191 Madison Blvd\n                \n            \n                            Suite A1\nMadison, Alabama 35758\n\n\n(256) 542-1415\n\n\n",
    "url": "https://www.psychologytoday.com/us/therapists/christy-dupree-elzer-williams-madison-al/246377"
  },
  {
    "address": "\n\n\n                    1909 Pleasant Drive\n                \nMuscle Shoals, Alabama 35661\n\n\n(256) 403-5619\n\n\n",
    "url": "https://www.psychologytoday.com/us/therapists/lynn-embry-muscle-shoals-al/94862"
  },
  {
    "address": "\n\n\n                    661 Helen Keller Blvd\n                \nTuscaloosa, Alabama 35404\n\n\n(205) 315-4662\n\n\n",
    "url": "https://www.psychologytoday.com/us/therapists/jared-emery-tuscaloosa-al/126019"
  },
  {
    "address": "\n\n                                        Laura English, Ph.D., Clinical Psychologist\n\n                    4000 Eagle Point Corporate Drive\n                \nBirmingham, Alabama 35242\n\n\n(205) 671-8108\n\n\n",
    "url": "https://www.psychologytoday.com/us/therapists/laura-l-english-birmingham-al/155453"
  },
  {
    "address": "\n\n                                        Down to Earth Counseling\n\n                    2804 8th Street\n                \nTuscaloosa, Alabama 35401\n\n\n(205) 610-9974\n\n\n",
    "url": "https://www.psychologytoday.com/us/therapists/greg-evans-tuscaloosa-al/64521"
  },
  {
    "address": "\n\n                                        New Hope Resources\n\n                    1109 Townhouse Road\n                \nHelena, Alabama 35080\n\n\n(205) 315-4580\n\n\n",
    "url": "https://www.psychologytoday.com/us/psychiatrists/david-r-faber-helena-al/123725"
  },
  {
    "address": "\n\n                                        North Counseling Services, LLC\n\n                    255 Grant St. SE\n                \n            \n                            Suite 303\nDecatur, Alabama 35601\n\n\n(256) 973-9453\n\n\n",
    "url": "https://www.psychologytoday.com/us/therapists/cindy-l-w-failing-decatur-al/338238"
  },
  {
    "address": "\n\n                                        Taylor Fair Counseling, LLC\n\n                    2127 14th Ave S\n                \nBirmingham, Alabama 35205\n\n\n(205) 509-1469\n\n\n",
    "url": "https://www.psychologytoday.com/us/therapists/taylor-fair-birmingham-al/351317"
  },
  {
    "address": "\n\n                                        Agape Individual and Family Therapy, LLC\n\n                    2805 7th Street\n                \nTuscaloosa, Alabama 35401\n\n\n(205) 512-2487\n\n\n",
    "url": "https://www.psychologytoday.com/us/therapists/greer-fawley-tuscaloosa-al/398143"
  },
  {
    "address": "\n\n                                        Auburn Psychology Group\n\n                    861 N Dean Rd\n                \nAuburn, Alabama 36830\n\n\n(334) 218-3908\n\n\n",
    "url": "https://www.psychologytoday.com/us/therapists/bill-r-ferguson-auburn-al/223050"
  },
  {
    "address": "\n\n                                        Laura Luckie Finch, LPC\n\n                    4 Office Park Circle\n                \n            \n                            Suite 203\nBirmingham, Alabama 35223\n\n\n(205) 512-3203\n\n\n",
    "url": "https://www.psychologytoday.com/us/therapists/laura-luckie-finch-birmingham-al/152387"
  },
  {
    "address": "\n\n\n                    300 Clinton Avenue West\n                \n            \n                            Suite 22A\nHuntsville, Alabama 35801\n\n\n(256) 666-2283\n\n\n",
    "url": "https://www.psychologytoday.com/us/therapists/kelly-s-fisher-huntsville-al/445537"
  },
  {
    "address": "\n\n                                        Revisions Counseling Center\n\n                    923 Stage Road Suite M\n                \nAuburn, Alabama 36830\n\n\n(334) 384-8861\n\n\n",
    "url": "https://www.psychologytoday.com/us/therapists/sloane-h-fitzgerald-auburn-al/328924"
  },
  {
    "address": "\n\n                                        Fitzpatrick and Watson Counseling, LLC\n\n                    600 Interstate Park Drive\n                \n            \n                            Suite 609\nMontgomery, Alabama 36109\n\n\n(334) 603-8983\n\n\n",
    "url": "https://www.psychologytoday.com/us/therapists/libby-fitzpatrick-montgomery-al/237084"
  },
  {
    "address": "\n\n                                        Comprehensive MedPsych Systems\n\n                    1110 Montlimar Place\n                \n            \n                            Suite 500\nMobile, Alabama 36609\n\n\n(251) 237-7719\n\n\n",
    "url": "https://www.psychologytoday.com/us/therapists/connie-vais-fleming-mobile-al/232594"
  },
  {
    "address": "\n\n\n                    Box 302\n                \nDothan, Alabama 36302\n\n\n(334) 292-2564\n\n\n",
    "url": "https://www.psychologytoday.com/us/therapists/tarama-lashay-fleming-dothan-al/352351"
  },
  {
    "address": "\n\n\n                     Executive Park Drive\n                \nOpelika, Alabama 36801\n\n\n(334) 319-9108\n\n\n",
    "url": "https://www.psychologytoday.com/us/therapists/sarah-flint-opelika-al/401666"
  },
  {
    "address": "\n\n\n                    2524 Valleydale Road\n                \n            \n                            Suite 100\nBirmingham, Alabama 35244\n\n\n(205) 619-6397 x3\n\n\n",
    "url": "https://www.psychologytoday.com/us/therapists/cheri-lynn-flow-birmingham-al/432514"
  },
  {
    "address": "\n\n                                        Lifestyle Therapy & Coaching\n\n                    7734 Madison Boulevard\n                \n            \n                            Suite 128\nHuntsville, Alabama 35806\n\nCall Rev. Joseph Follette Jr\n\n(256) 485-4769\n\n\n",
    "url": "https://www.psychologytoday.com/us/therapists/lifestyle-therapy-coaching-huntsville-al/104421"
  },
  {
    "address": "\n\n                                        Roots and Wings Therapy Center\n\n                    303 Williams Avenue\n                \n            \n                            Suite 221\nHuntsville, Alabama 35801\n\n\n(256) 858-7116\n\n\n",
    "url": "https://www.psychologytoday.com/us/therapists/anna-ford-smith-huntsville-al/130878"
  },
  {
    "address": "\n\n                                        Bay Area Clinical Associates\n\n                    3925 Spring Hill Avenue\n                \nMobile, Alabama 36608\n\n\n(251) 272-8504\n\n\n",
    "url": "https://www.psychologytoday.com/us/therapists/kelly-fountain-mobile-al/145368"
  },
  {
    "address": "\n\n                                        Family Consult Counseling Service\n\n                    1580 Sparkman Dr\n                \n            \n                            106\nHuntsville, Alabama 35816\n\nCall Dr. Kitson Francis\n\n(256) 743-6586\n\n\n",
    "url": "https://www.psychologytoday.com/us/therapists/family-consult-counseling-service-huntsville-al/375376"
  },
  {
    "address": "\n\n                                        Crisis Center, Inc.\n\n                    3600 8th Avenue South\n                \n            \n                            Suite 501\nBirmingham, Alabama 35222\n\nCall Emily Franklin\n\n(205) 614-5041\n\n\n",
    "url": "https://www.psychologytoday.com/us/therapists/crisis-center-inc-birmingham-al/394664"
  },
  {
    "address": "\n\n                                        Jerry Franks\n\n                    2603 Decatur Highway\n                \n            \n                            Suite 204\nGardendale, Alabama 35071\n\nCall Mr. Gerald Franks\n\n(205) 530-8971\n\n\n",
    "url": "https://www.psychologytoday.com/us/therapists/jerry-franks-gardendale-al/289005"
  },
  {
    "address": "\n\n                                        Work In Progress Counseling Services\n\n                    650 Energy Center Blvd\n                \n            \n                            Ste 1702\nNorthport, Alabama 35473\n\nCall Miss. Mechelle Frazier\n\n(205) 614-5030\n\n\n",
    "url": "https://www.psychologytoday.com/us/therapists/work-in-progress-counseling-northport-al/393159"
  },
  {
    "address": "\n\n\n                    800 Energy Center Boulevard\n                \n            \n                            Suite 1702\nNorthport, Alabama 35473\n\nCall Ms. Mechelle Frazier\n\n(855) 390-4557\n\n\n",
    "url": "https://www.psychologytoday.com/us/therapists/work-in-progress-counseling-service-llc-northport-al/453829"
  },
  {
    "address": "\n\n                                        Insight Therapeutic Services LLC\n\n                    1 Perimeter Park South\n                \n            \n                            Suite 100N\nBirmingham, Alabama 35243\n\nCall Ms. Victoria Frazier\n\n(205) 374-9859\n\n\n",
    "url": "https://www.psychologytoday.com/us/therapists/insight-therapeutic-services-llc-birmingham-al/329649"
  },
  {
    "address": "\n\n\n                    131 Fairhope Ave\n                \nFairhope, Alabama 36532\n\n\n(251) 829-7551\n\n\n",
    "url": "https://www.psychologytoday.com/us/therapists/france-m-frederick-fairhope-al/165083"
  },
  {
    "address": "\n\n\n                    4 Office Park Circle\n                \n            \n                            Suite 203\nBirmingham, Alabama 35223\n\n\n(256) 804-0641\n\n\n",
    "url": "https://www.psychologytoday.com/us/therapists/lauren-kasi-freeman-birmingham-al/404286"
  },
  {
    "address": "\n\n                                        John B French Alcohol and Drug Counseling\n\n                    166 Government Street\n                \n            \n                            Suite 200\nMobile, Alabama 36602\n\n\n(251) 732-2043\n\n\n",
    "url": "https://www.psychologytoday.com/us/therapists/john-b-french-mobile-al/132976"
  },
  {
    "address": "\n\n                                        Fry Behavioral Health, P.C.\n\n                    6 Office Park Circle\n                \n            \n                            Suite 318\nBirmingham, Alabama 35223\n\n\n(205) 623-2409\n\n\n",
    "url": "https://www.psychologytoday.com/us/therapists/rachel-fry-birmingham-al/226339"
  },
  {
    "address": "\n\n                                        Behavioral Sciences of Alabama\n\n                    810 Shoney Drive\n                \n            \n                            Suite 120\nHuntsville, Alabama 35801\n\nCall Mrs. Maggie Futch\n\n(256) 964-3029\n\n\n",
    "url": "https://www.psychologytoday.com/us/therapists/behavioral-sciences-of-alabama-huntsville-al/229792"
  },
  {
    "address": "\n\n                                        Elaine G. Rasco, L.L.C.\n\n                    3296 Cahaba Heights Rd\n                \n            \n                            Suite 110\nBirmingham, Alabama 35243\n\n\n(205) 928-3834\n\n\n",
    "url": "https://www.psychologytoday.com/us/therapists/mary-elaine-gamel-rasco-birmingham-al/234207"
  },
  {
    "address": "\n\n                                        Garrett Counseling\n\n                    1215 Jacksons Way SW\n                \nJacksonville, Alabama 36265\n\nCall Mrs. Ashley Garrett\n\n(256) 602-4486\n\n\n",
    "url": "https://www.psychologytoday.com/us/therapists/garrett-counseling-jacksonville-al/117276"
  },
  {
    "address": "\n\n                                        Pitts and Associates\n\n                    601 Beacon Parkway West\n                \n            \n                            Suite 201\nBirmingham, Alabama 35209\n\n\n(205) 236-5299\n\n\n",
    "url": "https://www.psychologytoday.com/us/therapists/w-lee-gaston-birmingham-al/386958"
  },
  {
    "address": "\n\n                                        Compass II Life Services, LLC\n\n                    PO BOX 1973\n                \nDaphne, Alabama 36526\n\n\n(251) 229-2860\n\n\n",
    "url": "https://www.psychologytoday.com/us/therapists/deon-gatson-daphne-al/238848"
  },
  {
    "address": "\n\n                                        Tranquil Minds Behavioral Health\n\n                    7738-B Madison Boulevard\n                \n            \n                            Suite 202\nHuntsville, Alabama 35806\n\n\n(256) 472-2902\n\n\n",
    "url": "https://www.psychologytoday.com/us/therapists/heather-m-gibbon-huntsville-al/301310"
  },
  {
    "address": "\n\n                                        Gibson Therapy Services, LLC\n\n                    2910 7th Street\n                \nTuscaloosa, Alabama 35401\n\nCall Mrs. Christie Gibson\n\n(205) 490-2574\n\n\n",
    "url": "https://www.psychologytoday.com/us/therapists/gibson-therapy-services-llc-tuscaloosa-al/167272"
  },
  {
    "address": "\n\n                                        Complete Counseling\n\n                    810 Regal Drive SW Suite Z\n                \nHuntsville, Alabama 35801\n\n\n(256) 384-8757\n\n\n",
    "url": "https://www.psychologytoday.com/us/therapists/jerry-u-gibson-huntsville-al/268148"
  },
  {
    "address": "\n\n\n                    106 Lee Street Northeast\n                \nDecatur, Alabama 35601\n\nCall Ms. Debra Gibson\n\n(256) 280-3954\n\n\n",
    "url": "https://www.psychologytoday.com/us/therapists/riverside-counseling-consulting-pc-decatur-al/434168"
  },
  {
    "address": "\n\n\n                    2910 Linden Ave\n                \n            \n                            Suite 101\nBirmingham, Alabama 35209\n\n\n(205) 419-0039\n\n\n",
    "url": "https://www.psychologytoday.com/us/therapists/ashley-gilbert-birmingham-al/112503"
  },
  {
    "address": "\n\n                                        The Healing Corner, LLC\n\n                    3413 A Rainbow Parkway\n                \nRainbow City, Alabama 35906\n\n\n(256) 727-6455\n\n\n",
    "url": "https://www.psychologytoday.com/us/therapists/tekeisha-goggins-rainbow-city-al/263679"
  }
]