[
  {
    "address": "\n\n                                        APH Addiction Clinic Suboxone Provider\n\n                    28740 US Highway 98\n                \n            \n                            Suite 9\nDaphne, Alabama 36526\n\nCall Dr. Magdi Tageldin\n\n(251) 290-8706\n\n\n",
    "url": "https://www.psychologytoday.com/us/psychiatrists/board-certified-addiction-psychiatrist-abpn-daphne-al/154847"
  },
  {
    "address": "\n\n\n                    111 Longwood Drive Southeast\n                \nHuntsville, Alabama 35801\n\n\n(256) 858-7160\n\n\n",
    "url": "https://www.psychologytoday.com/us/therapists/kenny-tannehill-huntsville-al/427725"
  },
  {
    "address": "\n\n                                        Alefyah Taqui, LLC\n\n                    605 Bel-air Blvd\n                \n            \n                            Suite 25\nMobile, Alabama 36606\n\n\n(251) 237-7494\n\n\n",
    "url": "https://www.psychologytoday.com/us/therapists/alefyah-alfy-taqui-mobile-al/348203"
  },
  {
    "address": "\n\n                                        Life Solutions\n\n                    1643 Slaughter Road\n                \nMadison, Alabama 35758\n\n\n(256) 414-8150\n\n\n",
    "url": "https://www.psychologytoday.com/us/therapists/mark-daniel-tate-madison-al/308344"
  },
  {
    "address": "\n\nBirmingham, Alabama 35209\n\n\n(205) 862-6254\n\n\n",
    "url": "https://www.psychologytoday.com/us/therapists/caroline-taylor-birmingham-al/124348"
  },
  {
    "address": "\n\n\n                    720 Energy Center Blvd, Suite 502\n                \nNorthport, Alabama 35473\n\n\n(205) 236-2240\n\n\n",
    "url": "https://www.psychologytoday.com/us/therapists/teresa-taylor-northport-al/304294"
  },
  {
    "address": "\n\n                                        TriCounty AID\n\n                    85 North Walston Bridge Road\n                \nJasper, Alabama 35504\n\n\n(205) 512-9108\n\n\n",
    "url": "https://www.psychologytoday.com/us/therapists/jennifer-terry-jasper-al/335158"
  },
  {
    "address": "\n\n                                        2101 Executive Park Drive\nOpelika, Alabama 36801\n\n\n(334) 319-9785\n\n\n",
    "url": "https://www.psychologytoday.com/us/therapists/albert-walter-thomas-opelika-al/294258"
  },
  {
    "address": "\n\n                                        Mollie Kelly Thomas, PhD, LLC\n\n                    1903 Oxmoor Road\n                \nBirmingham, Alabama 35209\n\n\n(205) 690-0926\n\n\n",
    "url": "https://www.psychologytoday.com/us/therapists/mollie-kelly-thomas-birmingham-al/49640"
  },
  {
    "address": "\n\n                                        Nancy W. Thomas Counseling Services, PLLC\n\n                    2835 Zelda Road\n                \n            \n                            Suite 6\nMontgomery, Alabama 36117\n\nCall Ms. Nancy Thomas\n\n(334) 721-8808\n\n\n",
    "url": "https://www.psychologytoday.com/us/therapists/nancy-w-thomas-counseling-services-pllc-montgomery-al/306713"
  },
  {
    "address": "\n\n\n                    1643 Slaughter Road\n                \nMadison, Alabama 35758\n\n\n(256) 369-0465\n\n\n",
    "url": "https://www.psychologytoday.com/us/therapists/isabella-thomas-heinsohn-madison-al/390774"
  },
  {
    "address": "\n\n                                        Muriel Thompson\n\n                    1037 22nd Street South\n                \n            \n                            Suite 200\nBirmingham, Alabama 35205\n\n\n(205) 377-0930\n\n\n",
    "url": "https://www.psychologytoday.com/us/therapists/muriel-c-thompson-birmingham-al/34555"
  },
  {
    "address": "\n\n\n                    3613 6th Avenue South\n                \nBirmingham, Alabama 35222\n\n\n(205) 236-5046\n\n\n",
    "url": "https://www.psychologytoday.com/us/therapists/valerie-thompson-birmingham-al/451690"
  },
  {
    "address": "\n\n                                        Trinity Counseling\n\n                    1025 Montgomery Highway\n                \nBirmingham, Alabama 35216\n\n\n(205) 386-6134\n\n\n",
    "url": "https://www.psychologytoday.com/us/therapists/sherer-boswell-thomson-birmingham-al/359387"
  },
  {
    "address": "\n\n                                        Warrior Wellness Group\n\n                    1130 1st Street North\n                \n            \n                            Suite 200\nAlabaster, Alabama 35007\n\n\n(205) 861-0057\n\n\n",
    "url": "https://www.psychologytoday.com/us/therapists/aisha-holmes-thorn-alabaster-al/366391"
  },
  {
    "address": "\n\n                                        Grayson and Associates\n\n                    4371 Narrow Lane Road\n                \nMontgomery, Alabama 36116\n\n\n(334) 234-2150\n\n\n",
    "url": "https://www.psychologytoday.com/us/therapists/michael-thornton-montgomery-al/343813"
  },
  {
    "address": "\n\n                                        The Hope Chest: Therapeutic Counseling Services\n\n                    224 Honeysuckle Road\n                \n            \n                            Suite 5\nDothan, Alabama 36305\n\n\n(334) 472-0158\n\n\n",
    "url": "https://www.psychologytoday.com/us/therapists/elizabeth-tindell-dothan-al/228061"
  },
  {
    "address": "\n\n                                        Blissful Mind Behavioral Health\nHuntsville, Alabama 35801\n\n\n(256) 667-8225\n\n\n",
    "url": "https://www.psychologytoday.com/us/therapists/pamela-tippit-huntsville-al/377860"
  },
  {
    "address": "\n\n                                        With Great Love, LLC\n\n                    1203 U.S. 98\n                \n            \n                            Suite 2A9\nDaphne, Alabama 36526\n\nCall Mrs. Emily Tisdale\n\n(833) 266-2186\n\n\n",
    "url": "https://www.psychologytoday.com/us/therapists/with-great-love-llc-daphne-al/449743"
  },
  {
    "address": "\n\n                                        Cardinal Counseling and Consulting\n\n                    1776 Independence Court\n                \n            \n                            Suite 103\nBirmingham, Alabama 35216\n\n\n(205) 623-5984\n\n\n",
    "url": "https://www.psychologytoday.com/us/therapists/michelle-torbor-birmingham-al/302385"
  },
  {
    "address": "\n\n                                        Level 3 Sports, LLC\nBirmingham, Alabama 35205\n\n\n(844) 618-3711\n\n\n",
    "url": "https://www.psychologytoday.com/us/therapists/dr-richard-trammel-birmingham-al/358788"
  },
  {
    "address": "\n\n                                        Level 3 Performance Psychology - Dr. Richard Trammel\nMountain Brook, Alabama 35223\n\nCall Dr. Richard Trammel\n\n(213) 279-6249\n\n\n",
    "url": "https://www.psychologytoday.com/us/therapists/level-3-sports-psychology-mountain-brook-al/407871"
  },
  {
    "address": "\n\n                                        Family Guidance Center of Alabama\n\n                    2358 Fairlane Drive\n                \n            \n                            Building G\nMontgomery, Alabama 36116\n\n\n(334) 518-3144\n\n\n",
    "url": "https://www.psychologytoday.com/us/therapists/sabrina-tran-montgomery-al/398847"
  },
  {
    "address": "\n\n                                        Revisions Counseling Center\n\n                    923 Stage Road\n                \n            \n                            Suite M\nAuburn, Alabama 36830\n\n\n(334) 231-6487\n\n\n",
    "url": "https://www.psychologytoday.com/us/therapists/joanna-hardman-treadwell-auburn-al/413020"
  },
  {
    "address": "\n\n\n                    7540 Cipriano Court\n                \n            \n                            Suite B\nFairhope, Alabama 36532\n\n\n(251) 270-4256\n\n\n",
    "url": "https://www.psychologytoday.com/us/psychiatrists/julie-t-trice-fairhope-al/444482"
  },
  {
    "address": "\n\n\n                    1736 Taliaferro Trail\n                \nMontgomery, Alabama 36117\n\n\n(334) 310-5935\n\n\n",
    "url": "https://www.psychologytoday.com/us/therapists/kristin-tubre-montgomery-al/173405"
  },
  {
    "address": "\n\n                                        Dr. Tucker & Associates Inc.\n\n                    1518D East Andrews Avenue\n                \nOzark, Alabama 36360\n\nCall Dr. Brent Tucker\n\n(334) 375-4061\n\n\n",
    "url": "https://www.psychologytoday.com/us/therapists/dr-tucker-associates-inc-ozark-al/191670"
  },
  {
    "address": "\n\n                                        Emily Tucker Counseling Services\n\n                    1940 Highway 33\n                \n            \n                            Unit A\nPelham, Alabama 35124\n\nCall Ms. Emily Tucker\n\n(205) 703-2843\n\n\n",
    "url": "https://www.psychologytoday.com/us/therapists/emily-tucker-counseling-services-pelham-al/158939"
  },
  {
    "address": "\n\n                                        Kellie Turchetta, LICSW\n\n                    2335 Pansy Street\n                \nHuntsville, Alabama 35801\n\n\n(256) 297-2571\n\n\n",
    "url": "https://www.psychologytoday.com/us/therapists/kellie-m-turchetta-huntsville-al/153324"
  },
  {
    "address": "\n\n                                        Auburn Professional Counseling\n\n                    311 N. College St. \n                \nAuburn, Alabama 36830\n\n\n(334) 231-6922\n\n\n",
    "url": "https://www.psychologytoday.com/us/therapists/jane-wallis-turnbull-humphries-auburn-al/214944"
  },
  {
    "address": "\n\n                                        The Bridges, A counseling place\n\n                    166 North Gay Street\n                \nAuburn, Alabama 36830\n\n\n(334) 603-0839\n\n\n",
    "url": "https://www.psychologytoday.com/us/therapists/kelly-cody-turner-auburn-al/379845"
  },
  {
    "address": "\n\n                                        Positive Changes, LLC\n\n                    114 Walker St\n                \nPrattville, Alabama 36066\n\nCall Dr. Melva Turner\n\n(334) 523-8734\n\n\n",
    "url": "https://www.psychologytoday.com/us/therapists/positive-changes-llc-prattville-al/57574"
  },
  {
    "address": "\n\n                                        Regina Turner, LLC\nBirmingham, Alabama 35244\n\nCall Mrs. Regina Turner\n\n(205) 509-2562\n\n\n",
    "url": "https://www.psychologytoday.com/us/therapists/regina-turner-llc-birmingham-al/359402"
  },
  {
    "address": "\n\nBirmingham, Alabama 35242\n\n\n(205) 315-4590\n\n\n",
    "url": "https://www.psychologytoday.com/us/therapists/bryan-tweed-birmingham-al/133684"
  }
]